epmatools/__init__.py
epmatools/datatables.py
epmatools/io.py
epmatools/maps.py
epmatools/minerals.py
epmatools/plotting.py
epmatools/data/maps/ex1.h5
epmatools/data/oxides/avgpelite.csv
epmatools/data/oxides/grt_profile.csv
epmatools/data/oxides/minerals.csv
epmatools/data/oxides/pyroxenes.csv
epmatools-0.3.2.dist-info/METADATA
epmatools-0.3.2.dist-info/WHEEL
epmatools-0.3.2.dist-info/licenses/COPYING.md
epmatools-0.3.2.dist-info/licenses/LICENSE.md
epmatools-0.3.2.dist-info/RECORD
