Metadata-Version: 2.4
Name: epmatools
Version: 0.3.2
Summary: Tools to manipulate EPMA analyses
Maintainer-email: Ondrej Lexa <lexa.ondrej@gmail.com>
License: MIT
License-File: COPYING.md
License-File: LICENSE.md
Classifier: License :: OSI Approved :: MIT License
Classifier: Operating System :: OS Independent
Classifier: Programming Language :: Python :: 3
Requires-Python: >=3.10
Requires-Dist: colorcet
Requires-Dist: h5py
Requires-Dist: jinja2
Requires-Dist: matplotlib
Requires-Dist: matplotlib-scalebar
Requires-Dist: numpy
Requires-Dist: openpyxl
Requires-Dist: pandas
Requires-Dist: periodictable
Requires-Dist: scikit-learn
Requires-Dist: scipy
Requires-Dist: xlrd
Provides-Extra: dev
Requires-Dist: black; extra == 'dev'
Requires-Dist: ipykernel; extra == 'dev'
Requires-Dist: jupyterlab; extra == 'dev'
Requires-Dist: nbsphinx; extra == 'dev'
Requires-Dist: nbsphinx-link; extra == 'dev'
Requires-Dist: nbval; extra == 'dev'
Requires-Dist: pytest; extra == 'dev'
Requires-Dist: pytest-cov; extra == 'dev'
Requires-Dist: sphinx; extra == 'dev'
Requires-Dist: sphinx-mdinclude; extra == 'dev'
Requires-Dist: sphinx-rtd-theme; extra == 'dev'
Provides-Extra: docs
Requires-Dist: ipykernel; extra == 'docs'
Requires-Dist: nbsphinx; extra == 'docs'
Requires-Dist: nbsphinx-link; extra == 'docs'
Requires-Dist: sphinx; extra == 'docs'
Requires-Dist: sphinx-mdinclude; extra == 'docs'
Requires-Dist: sphinx-rtd-theme; extra == 'docs'
Provides-Extra: extra
Requires-Dist: jupyterlab; extra == 'extra'
Provides-Extra: tests
Requires-Dist: nbval; extra == 'tests'
Requires-Dist: pytest; extra == 'tests'
Requires-Dist: pytest-cov; extra == 'tests'
